{"resolvedId":"C:/Users/tobis/gamesa-skola/src/root.css","transforms":[{"name":"__load__","result":"/* feel free to modify uno in here */","start":1676889523699,"end":1676889523699},{"name":"vite:css","result":"/* feel free to modify uno in here */","start":1676889523699,"end":1676889524596,"order":"normal"},{"name":"vite:css-post","result":"import { updateStyle as __vite__updateStyle, removeStyle as __vite__removeStyle } from \"/@vite/client\"\nconst __vite__id = \"C:/Users/tobis/gamesa-skola/src/root.css\"\nconst __vite__css = \"/* feel free to modify uno in here */\"\n__vite__updateStyle(__vite__id, __vite__css)\nimport.meta.hot.accept()\nexport default __vite__css\nimport.meta.hot.prune(() => __vite__removeStyle(__vite__id))","start":1676889524596,"end":1676889524596,"order":"normal"},{"name":"vite:import-analysis","result":"import { createHotContext as __vite__createHotContext } from \"/@vite/client\";import.meta.hot = __vite__createHotContext(\"/src/root.css\");import { updateStyle as __vite__updateStyle, removeStyle as __vite__removeStyle } from \"/@vite/client\"\nconst __vite__id = \"C:/Users/tobis/gamesa-skola/src/root.css\"\nconst __vite__css = \"/* feel free to modify uno in here */\"\n__vite__updateStyle(__vite__id, __vite__css)\nimport.meta.hot.accept()\nexport default __vite__css\nimport.meta.hot.prune(() => __vite__removeStyle(__vite__id))","start":1676889524596,"end":1676889524597,"order":"normal"}]}
