{"resolvedId":"C:/Users/tobis/gamesa-skola/node_modules/@tanstack/solid-query/build/solid/createInfiniteQuery.js?v=2f17421b","transforms":[{"name":"__load__","result":"import { InfiniteQueryObserver } from '@tanstack/query-core';\nimport { createBaseQuery } from './createBaseQuery';\nimport { createComputed } from 'solid-js';\nimport { createStore } from 'solid-js/store';\nimport { parseQueryArgs } from './utils';\nexport function createInfiniteQuery(arg1, arg2, arg3) {\n    // The parseQuery Args functions helps normalize the arguments into the correct form.\n    // Whatever the parameters are, they are normalized into the correct form.\n    const [parsedOptions, setParsedOptions] = createStore(parseQueryArgs(arg1, arg2, arg3));\n    // Watch for changes in the options and update the parsed options.\n    createComputed(() => {\n        const newParsedOptions = parseQueryArgs(arg1, arg2, arg3);\n        setParsedOptions(newParsedOptions);\n    });\n    return createBaseQuery(parsedOptions, InfiniteQueryObserver);\n}\n","start":1676889524115,"end":1676889524115},{"name":"vite:import-analysis","result":"import { InfiniteQueryObserver } from '/node_modules/@tanstack/query-core/build/lib/index.mjs?v=2f17421b';\nimport { createBaseQuery } from '/node_modules/@tanstack/solid-query/build/solid/createBaseQuery.js?v=2f17421b';\nimport { createComputed } from '/node_modules/.vite/deps/solid-js.js?v=53da11be';\nimport { createStore } from '/node_modules/.vite/deps/solid-js_store.js?v=53da11be';\nimport { parseQueryArgs } from '/node_modules/@tanstack/solid-query/build/solid/utils.js?v=2f17421b';\nexport function createInfiniteQuery(arg1, arg2, arg3) {\n    // The parseQuery Args functions helps normalize the arguments into the correct form.\n    // Whatever the parameters are, they are normalized into the correct form.\n    const [parsedOptions, setParsedOptions] = createStore(parseQueryArgs(arg1, arg2, arg3));\n    // Watch for changes in the options and update the parsed options.\n    createComputed(() => {\n        const newParsedOptions = parseQueryArgs(arg1, arg2, arg3);\n        setParsedOptions(newParsedOptions);\n    });\n    return createBaseQuery(parsedOptions, InfiniteQueryObserver);\n}\n","start":1676889524115,"end":1676889524121,"order":"normal"}]}
